iToolBox/__init__.py
iToolBox/tools.py
iToolBox-0.0.5.dist-info/LICENSE
iToolBox-0.0.5.dist-info/METADATA
iToolBox-0.0.5.dist-info/WHEEL
iToolBox-0.0.5.dist-info/top_level.txt
iToolBox-0.0.5.dist-info/RECORD
