Metadata-Version: 2.1
Name: iToolBox
Version: 0.0.5
Summary: A set of useful tools for my personal use.
Home-page: https://github.com/iBiology/iToolBox.git
Author: FEI YUAN
Author-email: yuanfeifuzzy@gmail.com
License: UNKNOWN
Project-URL: Bug Tracker, https://github.com/iBiology/iToolBox/issues
Platform: UNKNOWN
Classifier: Programming Language :: Python :: 3
Classifier: License :: OSI Approved :: MIT License
Classifier: Operating System :: POSIX
Requires-Python: >=3.6
License-File: LICENSE
